edgeql_queries/__init__.py
edgeql_queries/contrib/__init__.py
edgeql_queries/contrib/aiosql/__init__.py
edgeql_queries/contrib/aiosql/adapters.py
edgeql_queries/contrib/aiosql/queries.py
edgeql_queries/contrib/aiosql/query_loaders.py
edgeql_queries/exceptions.py
edgeql_queries/executors/__init__.py
edgeql_queries/executors/async_executor.py
edgeql_queries/executors/base_executor.py
edgeql_queries/executors/sync_executor.py
edgeql_queries/loaders.py
edgeql_queries/models.py
edgeql_queries/parsing.py
edgeql_queries/py.typed
edgeql_queries/queries.py
edgeql_queries/query_loaders.py
edgeql_queries/typing.py
edgeql_queries-0.4.0.dist-info/LICENSE
edgeql_queries-0.4.0.dist-info/WHEEL
edgeql_queries-0.4.0.dist-info/METADATA
edgeql_queries-0.4.0.dist-info/RECORD
