Metadata-Version: 2.1
Name: edgeql-queries
Version: 0.4.0
Summary: Simple EdgeQL in Python.
Home-page: https://github.com/nsidnev/edgeql-queries
License: FreeBSD
Author: Nik Sidnev
Author-email: sidnev.nick@gmail.com
Requires-Python: >=3.7,<4.0
Classifier: License :: Other/Proprietary License
Classifier: Programming Language :: Python :: 3
Classifier: Programming Language :: Python :: 3.10
Classifier: Programming Language :: Python :: 3.7
Classifier: Programming Language :: Python :: 3.8
Classifier: Programming Language :: Python :: 3.9
Requires-Dist: edgedb (>=0.19.0)
Project-URL: Documentation, https://nsidnev.github.io/edgeql-queries/
Project-URL: Repository, https://github.com/nsidnev/edgeql-queries
